[
    {
        "Image":"90dheu9w02",
        "Cmd":"CMD [\"/kto4jjri4jcript.py $CONFIG_FILE\"]",
        "Size":"903 B"
    },
    {
        "Image":"90oejwre20",
        "Cmd":"/biko3kokrok_RTG_SVC=9999 RMR_SEED_RT=/etc/xapp/routes.txt LD_LIBRARY_PATH=/usr/local/lib:/usr/local/libexec VERBOSE=0 CONFIG_FILE=/opt/ric/config/config-file.json",
        "Size":"6.4 MB"
    },
    {
        "Image":"lpekort8dce",
        "Cmd":"|2 SCHEMA_PATH=schemas STAGE_DIR=/tmp/helloworld-xapp /bin/sh -c sysctl -w net.ipv6.conf.lo.disable_ipv6=1",
        "Size":"90 B"
    },
    {
        "Image":"65748163aa8",
        "Cmd":"|2 SCHEMA_PATH=schemas STAGE_DIR=/tmp/helloworld-xapp /bin/sh -c ldconfig",
        "Size":"0 B"
    },
    {
        "Image":"dd50a527d01",
        "Cmd":"/bin/sh -c #(nop) COPY file:2604fef96634044eb359b0b58a8d56577c1afc9622ea9e307d5a23e5d68af5c7 in /usr/local/include/rnib/",
        "Size":"956 B"
    },
    {
        "Image":"47fcae6f92d",
        "Cmd":"/bin/sh -c #(nop) COPY file:240be01070b8c8a22af43bdfbad794cf6b63870787ebc606f907bcd6a79a4945 in /usr/local/include/rnib/",
        "Size":"900.8 MB"
    },
    {
        "Image":"65748163aa8",
        "Cmd":"|2 SCHEMA_PATH=schemas STAGE_DIR=/tmp/helloworld-xapp /bin/sh -c ldconfig",
        "Size":"0 B"
    },
    {
        "Image":"dd50a527d01",
        "Cmd":"/bin/sh -c #(nop) COPY file:2604fef96634044eb359b0b58a8d56577c1afc9622ea9e307d5a23e5d68af5c7 in /usr/local/include/rnib/",
        "Size":"956 B"
    },
    {
        "Image":"47fcae6f92d",
        "Cmd":"/bin/sh -c #(nop) COPY file:240be01070b8c8a22af43bdfbad794cf6b63870787ebc606f907bcd6a79a4945 in /usr/local/include/rnib/",
        "Size":"900.8 MB"
    }
]
